qrstu/__init__.py
qrstu/__main__.py
qrstu/commandline.py
qrstu/constants.py
qrstu/guess.py
qrstu/guess_data.py
qrstu/py.typed
qrstu/reduce.py
qrstu/transcode.py
qrstu-0.3.1.dist-info/LICENSE
qrstu-0.3.1.dist-info/METADATA
qrstu-0.3.1.dist-info/WHEEL
qrstu-0.3.1.dist-info/top_level.txt
qrstu-0.3.1.dist-info/RECORD
