Metadata-Version: 2.1
Name: qrstu
Version: 0.3.1
Summary: Q – Rainer Schwarzbach’s Text Utilities
Author-email: Rainer Schwarzbach <rainer@blackstream.de>
License: MIT License
Project-URL: Homepage, https://gitlab.com/blackstream-x/qrstu
Project-URL: Documentation, https://blackstream-x.gitlab.io/qrstu
Project-URL: CI, https://gitlab.com/blackstream-x/qrstu/-/pipelines
Project-URL: Bug Tracker, https://gitlab.com/blackstream-x/qrstu/-/issues
Project-URL: Repository, https://gitlab.com/blackstream-x/qrstu.git
Keywords: text,unicode,convert,transcode
Classifier: Development Status :: 4 - Beta
Classifier: License :: OSI Approved :: MIT License
Classifier: Operating System :: OS Independent
Classifier: Programming Language :: Python :: 3
Classifier: Programming Language :: Python :: 3.6
Classifier: Programming Language :: Python :: 3.7
Classifier: Programming Language :: Python :: 3.8
Classifier: Programming Language :: Python :: 3.9
Classifier: Programming Language :: Python :: 3.10
Classifier: Programming Language :: Python :: 3.11
Classifier: Programming Language :: Python :: 3.12
Classifier: Programming Language :: Python :: 3 :: Only
Requires-Python: >=3.6
License-File: LICENSE
